gigametr/__init__.py
gigametr/sbs.py
gigametr-0.3.0.dist-info/METADATA
gigametr-0.3.0.dist-info/WHEEL
gigametr-0.3.0.dist-info/top_level.txt
gigametr-0.3.0.dist-info/RECORD
