Metadata-Version: 2.4
Name: gigametr
Version: 0.3.0
Summary: Client for SBS tool
Home-page: https://github.com/averkij/lamm
Author: Sergei Averkiev
Author-email: averoo@gmail.com
Project-URL: Bug Tracker, https://github.com/averkij/lamm/issues
Classifier: Programming Language :: Python :: 3
Classifier: License :: OSI Approved :: GNU General Public License v3 (GPLv3)
Classifier: Operating System :: OS Independent
Requires-Python: >=3.6
